agent_tools/__init__.py
agent_tools/base.py
agent_tools/function/__init__.py
agent_tools/function/exceptions.py
agent_tools/function/func.py
agent_tools/function/json_type.py
agent_tools/function/parsers/__init__.py
agent_tools/function/parsers/abc.py
agent_tools/function/parsers/atomic_type_parser.py
agent_tools/function/parsers/bool_parser.py
agent_tools/function/parsers/dataclass_parser.py
agent_tools/function/parsers/default.py
agent_tools/function/parsers/dict_parser.py
agent_tools/function/parsers/enum_parser.py
agent_tools/function/parsers/float_parser.py
agent_tools/function/parsers/int_parser.py
agent_tools/function/parsers/list_parser.py
agent_tools/function/parsers/none_parser.py
agent_tools/function/parsers/str_parser.py
agent_tools/function/parsers/union_parser.py
agent_tool-0.1.6.dist-info/LICENSE
agent_tool-0.1.6.dist-info/METADATA
agent_tool-0.1.6.dist-info/WHEEL
agent_tool-0.1.6.dist-info/RECORD
