Metadata-Version: 2.1
Name: agent-tool
Version: 0.1.6
Summary: A protocol for AI agent tools
License: Apache 2.0
Author: Patrick Barker
Author-email: patrickbarkerco@gmail.com
Requires-Python: >=3.10,<4.0
Classifier: License :: Other/Proprietary License
Classifier: Programming Language :: Python :: 3
Classifier: Programming Language :: Python :: 3.10
Classifier: Programming Language :: Python :: 3.11
Requires-Dist: docstring-parser (>=0.15,<0.16)
